PythonPuppeteerClient/__init__.py
PythonPuppeteerClient/main.py
cloudbrowser_puppeteer_connector-0.1.3.dist-info/METADATA
cloudbrowser_puppeteer_connector-0.1.3.dist-info/WHEEL
cloudbrowser_puppeteer_connector-0.1.3.dist-info/top_level.txt
cloudbrowser_puppeteer_connector-0.1.3.dist-info/RECORD
