Metadata-Version: 2.1
Name: cloudbrowser-puppeteer-connector
Version: 0.1.3
Summary: Client for connection with CloudBrowser.
Author: cloudbrowser
Author-email: contact@cloudbrowser.ai
Classifier: Programming Language :: Python :: 3
Classifier: License :: OSI Approved :: MIT License
Classifier: Operating System :: OS Independent
Requires-Python: >=3.6
Requires-Dist: aiohttp>=3.7.0
Requires-Dist: pyppeteer>=0.2.5
Requires-Dist: asyncio
